[
  {
    "slug": "maths-iq",
    "tag": "Logic",
    "title": "IQ Test: Maths",
    "description": "Sharpen your mental arithmetic and pattern spotting.",
    "minutes": 3,
    "round_size": 5,
    "questions": [
      {
        "id": "mi1",
        "text": "What is 12 x 8?",
        "options": [
          {
            "t": "96",
            "c": true
          },
          {
            "t": "88",
            "c": false
          },
          {
            "t": "108",
            "c": false
          },
          {
            "t": "86",
            "c": false
          }
        ]
      },
      {
        "id": "mi2",
        "text": "Next number: 2, 4, 8, 16, ?",
        "options": [
          {
            "t": "24",
            "c": false
          },
          {
            "t": "32",
            "c": true
          },
          {
            "t": "20",
            "c": false
          },
          {
            "t": "18",
            "c": false
          }
        ]
      },
      {
        "id": "mi3",
        "text": "What is 15% of 200?",
        "options": [
          {
            "t": "25",
            "c": false
          },
          {
            "t": "35",
            "c": false
          },
          {
            "t": "30",
            "c": true
          },
          {
            "t": "20",
            "c": false
          }
        ]
      },
      {
        "id": "mi4",
        "text": "If x + 7 = 15, what is x?",
        "options": [
          {
            "t": "7",
            "c": false
          },
          {
            "t": "9",
            "c": false
          },
          {
            "t": "8",
            "c": true
          },
          {
            "t": "6",
            "c": false
          }
        ]
      },
      {
        "id": "mi5",
        "text": "What is the square root of 144?",
        "options": [
          {
            "t": "12",
            "c": true
          },
          {
            "t": "14",
            "c": false
          },
          {
            "t": "11",
            "c": false
          },
          {
            "t": "13",
            "c": false
          }
        ]
      },
      {
        "id": "mi6",
        "text": "What is 9 squared?",
        "options": [
          {
            "t": "81",
            "c": true
          },
          {
            "t": "72",
            "c": false
          },
          {
            "t": "91",
            "c": false
          },
          {
            "t": "18",
            "c": false
          }
        ]
      },
      {
        "id": "mi7",
        "text": "Next number: 1, 1, 2, 3, 5, ?",
        "options": [
          {
            "t": "6",
            "c": false
          },
          {
            "t": "8",
            "c": true
          },
          {
            "t": "7",
            "c": false
          },
          {
            "t": "9",
            "c": false
          }
        ]
      },
      {
        "id": "mi8",
        "text": "What is 100 divided by 4?",
        "options": [
          {
            "t": "20",
            "c": false
          },
          {
            "t": "25",
            "c": true
          },
          {
            "t": "30",
            "c": false
          },
          {
            "t": "24",
            "c": false
          }
        ]
      },
      {
        "id": "mi9",
        "text": "How many sides does a hexagon have?",
        "options": [
          {
            "t": "5",
            "c": false
          },
          {
            "t": "6",
            "c": true
          },
          {
            "t": "7",
            "c": false
          },
          {
            "t": "8",
            "c": false
          }
        ]
      },
      {
        "id": "mi10",
        "text": "What is 7 x 7?",
        "options": [
          {
            "t": "48",
            "c": false
          },
          {
            "t": "56",
            "c": false
          },
          {
            "t": "49",
            "c": true
          },
          {
            "t": "42",
            "c": false
          }
        ]
      },
      {
        "id": "mi11",
        "text": "Odd one out: 2, 3, 5, 9, 11",
        "options": [
          {
            "t": "3",
            "c": false
          },
          {
            "t": "9",
            "c": true
          },
          {
            "t": "5",
            "c": false
          },
          {
            "t": "11",
            "c": false
          }
        ]
      },
      {
        "id": "mi12",
        "text": "What is 1/4 as a percentage?",
        "options": [
          {
            "t": "20%",
            "c": false
          },
          {
            "t": "40%",
            "c": false
          },
          {
            "t": "25%",
            "c": true
          },
          {
            "t": "14%",
            "c": false
          }
        ]
      },
      {
        "id": "mi13",
        "text": "What is 15% of 80?",
        "options": [
          {
            "t": "12",
            "c": true
          },
          {
            "t": "15",
            "c": false
          },
          {
            "t": "8",
            "c": false
          },
          {
            "t": "20",
            "c": false
          }
        ]
      },
      {
        "id": "mi14",
        "text": "Solve: 3x = 21. What is x?",
        "options": [
          {
            "t": "6",
            "c": false
          },
          {
            "t": "7",
            "c": true
          },
          {
            "t": "8",
            "c": false
          },
          {
            "t": "9",
            "c": false
          }
        ]
      },
      {
        "id": "mi15",
        "text": "What is the next number: 3, 6, 12, 24, ?",
        "options": [
          {
            "t": "30",
            "c": false
          },
          {
            "t": "36",
            "c": false
          },
          {
            "t": "48",
            "c": true
          },
          {
            "t": "42",
            "c": false
          }
        ]
      },
      {
        "id": "mi16",
        "text": "What is 13 x 6?",
        "options": [
          {
            "t": "76",
            "c": false
          },
          {
            "t": "78",
            "c": true
          },
          {
            "t": "80",
            "c": false
          },
          {
            "t": "74",
            "c": false
          }
        ]
      },
      {
        "id": "mi17",
        "text": "A triangle's angles always add up to how many degrees?",
        "options": [
          {
            "t": "90",
            "c": false
          },
          {
            "t": "180",
            "c": true
          },
          {
            "t": "270",
            "c": false
          },
          {
            "t": "360",
            "c": false
          }
        ]
      },
      {
        "id": "mi18",
        "text": "What is 144 divided by 12?",
        "options": [
          {
            "t": "11",
            "c": false
          },
          {
            "t": "12",
            "c": true
          },
          {
            "t": "13",
            "c": false
          },
          {
            "t": "14",
            "c": false
          }
        ]
      },
      {
        "id": "mi19",
        "text": "If a shirt costs $40 and is discounted 25%, what is the sale price?",
        "options": [
          {
            "t": "$30",
            "c": true
          },
          {
            "t": "$35",
            "c": false
          },
          {
            "t": "$32",
            "c": false
          },
          {
            "t": "$28",
            "c": false
          }
        ]
      },
      {
        "id": "mi20",
        "text": "What is the value of 2 to the power of 5?",
        "options": [
          {
            "t": "16",
            "c": false
          },
          {
            "t": "32",
            "c": true
          },
          {
            "t": "64",
            "c": false
          },
          {
            "t": "25",
            "c": false
          }
        ]
      },
      {
        "id": "mi21",
        "text": "Odd one out: 4, 8, 15, 16, 24",
        "options": [
          {
            "t": "15",
            "c": true
          },
          {
            "t": "8",
            "c": false
          },
          {
            "t": "16",
            "c": false
          },
          {
            "t": "24",
            "c": false
          }
        ]
      },
      {
        "id": "mi22",
        "text": "What is the perimeter of a square with side length 6?",
        "options": [
          {
            "t": "12",
            "c": false
          },
          {
            "t": "24",
            "c": true
          },
          {
            "t": "36",
            "c": false
          },
          {
            "t": "18",
            "c": false
          }
        ]
      },
      {
        "id": "mi23",
        "text": "Next number: 1, 4, 9, 16, ?",
        "options": [
          {
            "t": "20",
            "c": false
          },
          {
            "t": "25",
            "c": true
          },
          {
            "t": "22",
            "c": false
          },
          {
            "t": "30",
            "c": false
          }
        ]
      },
      {
        "id": "mi24",
        "text": "What is 0.5 as a fraction in simplest form?",
        "options": [
          {
            "t": "1/5",
            "c": false
          },
          {
            "t": "1/2",
            "c": true
          },
          {
            "t": "2/5",
            "c": false
          },
          {
            "t": "5/10",
            "c": false
          }
        ]
      },
      {
        "id": "mi25",
        "text": "What is 6 factorial (6!) equal to?",
        "options": [
          {
            "t": "360",
            "c": false
          },
          {
            "t": "620",
            "c": false
          },
          {
            "t": "720",
            "c": true
          },
          {
            "t": "120",
            "c": false
          }
        ]
      },
      {
        "id": "mi26",
        "text": "What is the area of a rectangle 5 by 8?",
        "options": [
          {
            "t": "13",
            "c": false
          },
          {
            "t": "40",
            "c": true
          },
          {
            "t": "35",
            "c": false
          },
          {
            "t": "45",
            "c": false
          }
        ]
      },
      {
        "id": "mi27",
        "text": "If y = 2x + 3 and x = 4, what is y?",
        "options": [
          {
            "t": "9",
            "c": false
          },
          {
            "t": "11",
            "c": true
          },
          {
            "t": "10",
            "c": false
          },
          {
            "t": "14",
            "c": false
          }
        ]
      },
      {
        "id": "mi28",
        "text": "What is the sum of the first 5 positive integers?",
        "options": [
          {
            "t": "10",
            "c": false
          },
          {
            "t": "15",
            "c": true
          },
          {
            "t": "20",
            "c": false
          },
          {
            "t": "25",
            "c": false
          }
        ]
      },
      {
        "id": "mi29",
        "text": "Which number is prime?",
        "options": [
          {
            "t": "21",
            "c": false
          },
          {
            "t": "27",
            "c": false
          },
          {
            "t": "29",
            "c": true
          },
          {
            "t": "33",
            "c": false
          }
        ]
      },
      {
        "id": "mi30",
        "text": "What is 3/4 expressed as a percentage?",
        "options": [
          {
            "t": "34%",
            "c": false
          },
          {
            "t": "75%",
            "c": true
          },
          {
            "t": "43%",
            "c": false
          },
          {
            "t": "57%",
            "c": false
          }
        ]
      },
      {
        "id": "mi31",
        "text": "What is the average of 4, 8, and 12?",
        "options": [
          {
            "t": "6",
            "c": false
          },
          {
            "t": "8",
            "c": true
          },
          {
            "t": "10",
            "c": false
          },
          {
            "t": "12",
            "c": false
          }
        ]
      },
      {
        "id": "mi32",
        "text": "Next number: 100, 90, 80, 70, ?",
        "options": [
          {
            "t": "50",
            "c": false
          },
          {
            "t": "65",
            "c": false
          },
          {
            "t": "60",
            "c": true
          },
          {
            "t": "55",
            "c": false
          }
        ]
      }
    ]
  },
  {
    "slug": "family-quiz",
    "tag": "Lifestyle",
    "title": "Family Quiz",
    "description": "Fun questions about family life, traditions, and bonds.",
    "minutes": 2,
    "round_size": 5,
    "questions": [
      {
        "id": "fq1",
        "text": "A gathering of extended family is often called a...",
        "options": [
          {
            "t": "Reunion",
            "c": true
          },
          {
            "t": "Meeting",
            "c": false
          },
          {
            "t": "Session",
            "c": false
          },
          {
            "t": "Conference",
            "c": false
          }
        ]
      },
      {
        "id": "fq2",
        "text": "Which of these is a common family bonding activity?",
        "options": [
          {
            "t": "Filing taxes separately",
            "c": false
          },
          {
            "t": "Eating meals together",
            "c": true
          },
          {
            "t": "Avoiding each other",
            "c": false
          },
          {
            "t": "Working night shifts",
            "c": false
          }
        ]
      },
      {
        "id": "fq3",
        "text": "What do many families celebrate yearly to mark someone's birth?",
        "options": [
          {
            "t": "Anniversary",
            "c": false
          },
          {
            "t": "Birthday",
            "c": true
          },
          {
            "t": "Graduation",
            "c": false
          },
          {
            "t": "Promotion",
            "c": false
          }
        ]
      },
      {
        "id": "fq4",
        "text": "A person's mother and father together are called their...",
        "options": [
          {
            "t": "Siblings",
            "c": false
          },
          {
            "t": "Parents",
            "c": true
          },
          {
            "t": "Cousins",
            "c": false
          },
          {
            "t": "In-laws",
            "c": false
          }
        ]
      },
      {
        "id": "fq5",
        "text": "What is a common name for your parent's parent?",
        "options": [
          {
            "t": "Grandparent",
            "c": true
          },
          {
            "t": "Godparent",
            "c": false
          },
          {
            "t": "Stepparent",
            "c": false
          },
          {
            "t": "Guardian",
            "c": false
          }
        ]
      },
      {
        "id": "fq6",
        "text": "Which of these best describes a 'family tree'?",
        "options": [
          {
            "t": "A tree planted at birth",
            "c": false
          },
          {
            "t": "A diagram of family relationships",
            "c": true
          },
          {
            "t": "A type of oak tree",
            "c": false
          },
          {
            "t": "A family business",
            "c": false
          }
        ]
      },
      {
        "id": "fq7",
        "text": "Your sibling's child is your...",
        "options": [
          {
            "t": "Nephew or niece",
            "c": true
          },
          {
            "t": "Cousin",
            "c": false
          },
          {
            "t": "Grandchild",
            "c": false
          },
          {
            "t": "In-law",
            "c": false
          }
        ]
      },
      {
        "id": "fq8",
        "text": "What's a common way families stay in touch across distances?",
        "options": [
          {
            "t": "Ignoring each other",
            "c": false
          },
          {
            "t": "Video calls",
            "c": true
          },
          {
            "t": "Writing nothing",
            "c": false
          },
          {
            "t": "Moving further apart",
            "c": false
          }
        ]
      },
      {
        "id": "fq9",
        "text": "What do many cultures call a family celebration of marriage?",
        "options": [
          {
            "t": "Wedding",
            "c": true
          },
          {
            "t": "Funeral",
            "c": false
          },
          {
            "t": "Retirement",
            "c": false
          },
          {
            "t": "Audit",
            "c": false
          }
        ]
      },
      {
        "id": "fq10",
        "text": "Which quality is most associated with strong family bonds?",
        "options": [
          {
            "t": "Trust and communication",
            "c": true
          },
          {
            "t": "Distance",
            "c": false
          },
          {
            "t": "Silence",
            "c": false
          },
          {
            "t": "Competition",
            "c": false
          }
        ]
      },
      {
        "id": "fq11",
        "text": "What do you call your father's brother?",
        "options": [
          {
            "t": "Uncle",
            "c": true
          },
          {
            "t": "Cousin",
            "c": false
          },
          {
            "t": "Nephew",
            "c": false
          },
          {
            "t": "In-law",
            "c": false
          }
        ]
      },
      {
        "id": "fq12",
        "text": "What is a common term for your spouse's parents?",
        "options": [
          {
            "t": "In-laws",
            "c": true
          },
          {
            "t": "Step-parents",
            "c": false
          },
          {
            "t": "Guardians",
            "c": false
          },
          {
            "t": "Godparents",
            "c": false
          }
        ]
      },
      {
        "id": "fq13",
        "text": "What is it called when a family adopts a child?",
        "options": [
          {
            "t": "Adoption",
            "c": true
          },
          {
            "t": "Fostering only",
            "c": false
          },
          {
            "t": "Guardianship only",
            "c": false
          },
          {
            "t": "Custody transfer",
            "c": false
          }
        ]
      },
      {
        "id": "fq14",
        "text": "Twins born from the same pregnancy are called what if they look identical?",
        "options": [
          {
            "t": "Identical twins",
            "c": true
          },
          {
            "t": "Fraternal twins",
            "c": false
          },
          {
            "t": "Conjoined twins",
            "c": false
          },
          {
            "t": "Half-twins",
            "c": false
          }
        ]
      },
      {
        "id": "fq15",
        "text": "What do you call your mother's sister?",
        "options": [
          {
            "t": "Aunt",
            "c": true
          },
          {
            "t": "Grandmother",
            "c": false
          },
          {
            "t": "Niece",
            "c": false
          },
          {
            "t": "Cousin",
            "c": false
          }
        ]
      },
      {
        "id": "fq16",
        "text": "A family gathering to honor someone's memory after death is called a?",
        "options": [
          {
            "t": "Funeral/memorial",
            "c": true
          },
          {
            "t": "Wedding",
            "c": false
          },
          {
            "t": "Reunion",
            "c": false
          },
          {
            "t": "Shower",
            "c": false
          }
        ]
      },
      {
        "id": "fq17",
        "text": "What is the term for children of the same parents?",
        "options": [
          {
            "t": "Siblings",
            "c": true
          },
          {
            "t": "In-laws",
            "c": false
          },
          {
            "t": "Cousins",
            "c": false
          },
          {
            "t": "Relatives only",
            "c": false
          }
        ]
      },
      {
        "id": "fq18",
        "text": "A party celebrating an upcoming baby is often called a?",
        "options": [
          {
            "t": "Baby shower",
            "c": true
          },
          {
            "t": "Baby reunion",
            "c": false
          },
          {
            "t": "Baby festival",
            "c": false
          },
          {
            "t": "Baby gala",
            "c": false
          }
        ]
      },
      {
        "id": "fq19",
        "text": "What is a common term for a family's line of ancestors?",
        "options": [
          {
            "t": "Lineage/ancestry",
            "c": true
          },
          {
            "t": "Community",
            "c": false
          },
          {
            "t": "Household",
            "c": false
          },
          {
            "t": "Estate",
            "c": false
          }
        ]
      },
      {
        "id": "fq20",
        "text": "What do you call the relationship between people who marry into your family?",
        "options": [
          {
            "t": "In-laws",
            "c": true
          },
          {
            "t": "Blood relatives",
            "c": false
          },
          {
            "t": "Guardians",
            "c": false
          },
          {
            "t": "Dependents",
            "c": false
          }
        ]
      },
      {
        "id": "fq21",
        "text": "What is it called when parents separate legally?",
        "options": [
          {
            "t": "Divorce",
            "c": true
          },
          {
            "t": "Adoption",
            "c": false
          },
          {
            "t": "Custody only",
            "c": false
          },
          {
            "t": "Annulment always",
            "c": false
          }
        ]
      },
      {
        "id": "fq22",
        "text": "What do most cultures call the celebration marking a wedding anniversary?",
        "options": [
          {
            "t": "Anniversary",
            "c": true
          },
          {
            "t": "Reunion",
            "c": false
          },
          {
            "t": "Jubilee only",
            "c": false
          },
          {
            "t": "Festival",
            "c": false
          }
        ]
      },
      {
        "id": "fq23",
        "text": "What is the relationship between two people who share the same grandparents but not parents?",
        "options": [
          {
            "t": "Cousins",
            "c": true
          },
          {
            "t": "Siblings",
            "c": false
          },
          {
            "t": "Nephews",
            "c": false
          },
          {
            "t": "In-laws",
            "c": false
          }
        ]
      },
      {
        "id": "fq24",
        "text": "What do you call a family member who looks after a child when parents cannot?",
        "options": [
          {
            "t": "Guardian",
            "c": true
          },
          {
            "t": "Landlord",
            "c": false
          },
          {
            "t": "Employer",
            "c": false
          },
          {
            "t": "Tutor only",
            "c": false
          }
        ]
      },
      {
        "id": "fq25",
        "text": "A meal shared by the whole family, especially on holidays, is often centered around what?",
        "options": [
          {
            "t": "Togetherness/tradition",
            "c": true
          },
          {
            "t": "Business",
            "c": false
          },
          {
            "t": "Competition",
            "c": false
          },
          {
            "t": "Silence",
            "c": false
          }
        ]
      },
      {
        "id": "fq26",
        "text": "What is a common way grandparents pass down family history?",
        "options": [
          {
            "t": "Storytelling",
            "c": true
          },
          {
            "t": "Contracts",
            "c": false
          },
          {
            "t": "Exams",
            "c": false
          },
          {
            "t": "Advertising",
            "c": false
          }
        ]
      },
      {
        "id": "fq27",
        "text": "What do you call your child's spouse?",
        "options": [
          {
            "t": "Son-in-law/daughter-in-law",
            "c": true
          },
          {
            "t": "Step-child",
            "c": false
          },
          {
            "t": "Ward",
            "c": false
          },
          {
            "t": "Heir only",
            "c": false
          }
        ]
      },
      {
        "id": "fq28",
        "text": "What is it called when a family moves together to a new home?",
        "options": [
          {
            "t": "Relocating/moving",
            "c": true
          },
          {
            "t": "Migrating always",
            "c": false
          },
          {
            "t": "Touring",
            "c": false
          },
          {
            "t": "Commuting",
            "c": false
          }
        ]
      },
      {
        "id": "fq29",
        "text": "What is a common value most families try to build among members?",
        "options": [
          {
            "t": "Trust",
            "c": true
          },
          {
            "t": "Rivalry",
            "c": false
          },
          {
            "t": "Distance",
            "c": false
          },
          {
            "t": "Secrecy",
            "c": false
          }
        ]
      },
      {
        "id": "fq30",
        "text": "What do you call the youngest child in a family?",
        "options": [
          {
            "t": "The youngest/last-born",
            "c": true
          },
          {
            "t": "The firstborn",
            "c": false
          },
          {
            "t": "The only child always",
            "c": false
          },
          {
            "t": "The middle child",
            "c": false
          }
        ]
      }
    ]
  },
  {
    "slug": "science-quiz",
    "tag": "STEM",
    "title": "Science Quiz",
    "description": "From chemistry to biology \u2014 how sharp is your science?",
    "minutes": 3,
    "round_size": 5,
    "questions": [
      {
        "id": "sc1",
        "text": "What gas do plants absorb from the atmosphere?",
        "options": [
          {
            "t": "Oxygen",
            "c": false
          },
          {
            "t": "Nitrogen",
            "c": false
          },
          {
            "t": "Carbon dioxide",
            "c": true
          },
          {
            "t": "Hydrogen",
            "c": false
          }
        ]
      },
      {
        "id": "sc2",
        "text": "What is H2O more commonly known as?",
        "options": [
          {
            "t": "Salt",
            "c": false
          },
          {
            "t": "Water",
            "c": true
          },
          {
            "t": "Sugar",
            "c": false
          },
          {
            "t": "Oxygen",
            "c": false
          }
        ]
      },
      {
        "id": "sc3",
        "text": "Which organ pumps blood around the body?",
        "options": [
          {
            "t": "Lungs",
            "c": false
          },
          {
            "t": "Liver",
            "c": false
          },
          {
            "t": "Heart",
            "c": true
          },
          {
            "t": "Kidney",
            "c": false
          }
        ]
      },
      {
        "id": "sc4",
        "text": "What force pulls objects toward Earth?",
        "options": [
          {
            "t": "Magnetism",
            "c": false
          },
          {
            "t": "Gravity",
            "c": true
          },
          {
            "t": "Friction",
            "c": false
          },
          {
            "t": "Tension",
            "c": false
          }
        ]
      },
      {
        "id": "sc5",
        "text": "Which planet is known as the Red Planet?",
        "options": [
          {
            "t": "Venus",
            "c": false
          },
          {
            "t": "Mars",
            "c": true
          },
          {
            "t": "Jupiter",
            "c": false
          },
          {
            "t": "Mercury",
            "c": false
          }
        ]
      },
      {
        "id": "sc6",
        "text": "What is the basic unit of life?",
        "options": [
          {
            "t": "Atom",
            "c": false
          },
          {
            "t": "Cell",
            "c": true
          },
          {
            "t": "Molecule",
            "c": false
          },
          {
            "t": "Tissue",
            "c": false
          }
        ]
      },
      {
        "id": "sc7",
        "text": "What do we call animals that eat only plants?",
        "options": [
          {
            "t": "Carnivores",
            "c": false
          },
          {
            "t": "Herbivores",
            "c": true
          },
          {
            "t": "Omnivores",
            "c": false
          },
          {
            "t": "Predators",
            "c": false
          }
        ]
      },
      {
        "id": "sc8",
        "text": "Which gas do humans exhale the most of?",
        "options": [
          {
            "t": "Oxygen",
            "c": false
          },
          {
            "t": "Carbon dioxide",
            "c": true
          },
          {
            "t": "Helium",
            "c": false
          },
          {
            "t": "Nitrogen",
            "c": false
          }
        ]
      },
      {
        "id": "sc9",
        "text": "What is the boiling point of water at sea level (Celsius)?",
        "options": [
          {
            "t": "90\u00b0C",
            "c": false
          },
          {
            "t": "100\u00b0C",
            "c": true
          },
          {
            "t": "120\u00b0C",
            "c": false
          },
          {
            "t": "80\u00b0C",
            "c": false
          }
        ]
      },
      {
        "id": "sc10",
        "text": "Which part of the cell contains genetic material?",
        "options": [
          {
            "t": "Nucleus",
            "c": true
          },
          {
            "t": "Membrane",
            "c": false
          },
          {
            "t": "Cytoplasm",
            "c": false
          },
          {
            "t": "Wall",
            "c": false
          }
        ]
      },
      {
        "id": "sc11",
        "text": "What natural phenomenon is caused by the Earth spinning on its axis?",
        "options": [
          {
            "t": "Seasons",
            "c": false
          },
          {
            "t": "Day and night",
            "c": true
          },
          {
            "t": "Tides",
            "c": false
          },
          {
            "t": "Earthquakes",
            "c": false
          }
        ]
      },
      {
        "id": "sc12",
        "text": "Which of these is a renewable energy source?",
        "options": [
          {
            "t": "Coal",
            "c": false
          },
          {
            "t": "Solar power",
            "c": true
          },
          {
            "t": "Natural gas",
            "c": false
          },
          {
            "t": "Petroleum",
            "c": false
          }
        ]
      },
      {
        "id": "sc13",
        "text": "What is the chemical symbol for gold?",
        "options": [
          {
            "t": "Au",
            "c": true
          },
          {
            "t": "Ag",
            "c": false
          },
          {
            "t": "Go",
            "c": false
          },
          {
            "t": "Gd",
            "c": false
          }
        ]
      },
      {
        "id": "sc14",
        "text": "What is the powerhouse of the cell?",
        "options": [
          {
            "t": "Nucleus",
            "c": false
          },
          {
            "t": "Mitochondria",
            "c": true
          },
          {
            "t": "Ribosome",
            "c": false
          },
          {
            "t": "Cytoplasm",
            "c": false
          }
        ]
      },
      {
        "id": "sc15",
        "text": "What is the process by which plants make food using sunlight?",
        "options": [
          {
            "t": "Photosynthesis",
            "c": true
          },
          {
            "t": "Respiration",
            "c": false
          },
          {
            "t": "Digestion",
            "c": false
          },
          {
            "t": "Fermentation",
            "c": false
          }
        ]
      },
      {
        "id": "sc16",
        "text": "What is the closest star to Earth?",
        "options": [
          {
            "t": "The Sun",
            "c": true
          },
          {
            "t": "Proxima Centauri",
            "c": false
          },
          {
            "t": "Sirius",
            "c": false
          },
          {
            "t": "Alpha Centauri",
            "c": false
          }
        ]
      },
      {
        "id": "sc17",
        "text": "What state of matter has no fixed shape or volume?",
        "options": [
          {
            "t": "Gas",
            "c": true
          },
          {
            "t": "Solid",
            "c": false
          },
          {
            "t": "Liquid",
            "c": false
          },
          {
            "t": "Plasma only",
            "c": false
          }
        ]
      },
      {
        "id": "sc18",
        "text": "What is the study of living organisms called?",
        "options": [
          {
            "t": "Biology",
            "c": true
          },
          {
            "t": "Geology",
            "c": false
          },
          {
            "t": "Chemistry",
            "c": false
          },
          {
            "t": "Physics",
            "c": false
          }
        ]
      },
      {
        "id": "sc19",
        "text": "How many bones are in the adult human body?",
        "options": [
          {
            "t": "206",
            "c": true
          },
          {
            "t": "186",
            "c": false
          },
          {
            "t": "226",
            "c": false
          },
          {
            "t": "196",
            "c": false
          }
        ]
      },
      {
        "id": "sc20",
        "text": "What gas makes up most of Earth's atmosphere?",
        "options": [
          {
            "t": "Nitrogen",
            "c": true
          },
          {
            "t": "Oxygen",
            "c": false
          },
          {
            "t": "Carbon dioxide",
            "c": false
          },
          {
            "t": "Helium",
            "c": false
          }
        ]
      },
      {
        "id": "sc21",
        "text": "What force keeps planets in orbit around the sun?",
        "options": [
          {
            "t": "Gravity",
            "c": true
          },
          {
            "t": "Magnetism",
            "c": false
          },
          {
            "t": "Friction",
            "c": false
          },
          {
            "t": "Inertia alone",
            "c": false
          }
        ]
      },
      {
        "id": "sc22",
        "text": "What is the chemical formula for table salt?",
        "options": [
          {
            "t": "NaCl",
            "c": true
          },
          {
            "t": "KCl",
            "c": false
          },
          {
            "t": "CaCl2",
            "c": false
          },
          {
            "t": "NaOH",
            "c": false
          }
        ]
      },
      {
        "id": "sc23",
        "text": "Which organ filters waste from the blood?",
        "options": [
          {
            "t": "Kidneys",
            "c": true
          },
          {
            "t": "Liver only",
            "c": false
          },
          {
            "t": "Lungs",
            "c": false
          },
          {
            "t": "Stomach",
            "c": false
          }
        ]
      },
      {
        "id": "sc24",
        "text": "What is the smallest unit of an element that retains its properties?",
        "options": [
          {
            "t": "Atom",
            "c": true
          },
          {
            "t": "Molecule",
            "c": false
          },
          {
            "t": "Cell",
            "c": false
          },
          {
            "t": "Proton",
            "c": false
          }
        ]
      },
      {
        "id": "sc25",
        "text": "What type of energy does a moving object have?",
        "options": [
          {
            "t": "Kinetic energy",
            "c": true
          },
          {
            "t": "Potential energy",
            "c": false
          },
          {
            "t": "Thermal energy only",
            "c": false
          },
          {
            "t": "Chemical energy",
            "c": false
          }
        ]
      },
      {
        "id": "sc26",
        "text": "Which blood type is considered the universal donor?",
        "options": [
          {
            "t": "O negative",
            "c": true
          },
          {
            "t": "AB positive",
            "c": false
          },
          {
            "t": "A positive",
            "c": false
          },
          {
            "t": "B negative",
            "c": false
          }
        ]
      },
      {
        "id": "sc27",
        "text": "What is the term for animals that are active at night?",
        "options": [
          {
            "t": "Nocturnal",
            "c": true
          },
          {
            "t": "Diurnal",
            "c": false
          },
          {
            "t": "Crepuscular only",
            "c": false
          },
          {
            "t": "Hibernating",
            "c": false
          }
        ]
      },
      {
        "id": "sc28",
        "text": "What layer of the Earth is molten rock found in?",
        "options": [
          {
            "t": "Mantle",
            "c": true
          },
          {
            "t": "Crust",
            "c": false
          },
          {
            "t": "Inner core only",
            "c": false
          },
          {
            "t": "Atmosphere",
            "c": false
          }
        ]
      },
      {
        "id": "sc29",
        "text": "What vitamin does sunlight help the body produce?",
        "options": [
          {
            "t": "Vitamin D",
            "c": true
          },
          {
            "t": "Vitamin C",
            "c": false
          },
          {
            "t": "Vitamin A",
            "c": false
          },
          {
            "t": "Vitamin B12",
            "c": false
          }
        ]
      },
      {
        "id": "sc30",
        "text": "What is the process of a caterpillar becoming a butterfly called?",
        "options": [
          {
            "t": "Metamorphosis",
            "c": true
          },
          {
            "t": "Pollination",
            "c": false
          },
          {
            "t": "Germination",
            "c": false
          },
          {
            "t": "Hibernation",
            "c": false
          }
        ]
      },
      {
        "id": "sc31",
        "text": "What is the main gas plants release during photosynthesis?",
        "options": [
          {
            "t": "Oxygen",
            "c": true
          },
          {
            "t": "Carbon dioxide",
            "c": false
          },
          {
            "t": "Nitrogen",
            "c": false
          },
          {
            "t": "Hydrogen",
            "c": false
          }
        ]
      },
      {
        "id": "sc32",
        "text": "What is the term for the distance light travels in one year?",
        "options": [
          {
            "t": "A light-year",
            "c": true
          },
          {
            "t": "A parsec only",
            "c": false
          },
          {
            "t": "An astronomical unit",
            "c": false
          },
          {
            "t": "A light-day",
            "c": false
          }
        ]
      }
    ]
  },
  {
    "slug": "intelligence-quiz",
    "tag": "Trivia",
    "title": "Intelligence Quiz",
    "description": "General knowledge questions covering the world's sharpest minds.",
    "minutes": 2,
    "round_size": 5,
    "questions": [
      {
        "id": "iq1",
        "text": "Who developed the theory of relativity?",
        "options": [
          {
            "t": "Isaac Newton",
            "c": false
          },
          {
            "t": "Albert Einstein",
            "c": true
          },
          {
            "t": "Nikola Tesla",
            "c": false
          },
          {
            "t": "Galileo Galilei",
            "c": false
          }
        ]
      },
      {
        "id": "iq2",
        "text": "IQ stands for which of these?",
        "options": [
          {
            "t": "Intelligence Quotient",
            "c": true
          },
          {
            "t": "Instant Question",
            "c": false
          },
          {
            "t": "Inner Quality",
            "c": false
          },
          {
            "t": "Intellect Quality",
            "c": false
          }
        ]
      },
      {
        "id": "iq3",
        "text": "Which of these is a sign of critical thinking?",
        "options": [
          {
            "t": "Accepting all claims blindly",
            "c": false
          },
          {
            "t": "Questioning evidence",
            "c": true
          },
          {
            "t": "Ignoring facts",
            "c": false
          },
          {
            "t": "Avoiding new ideas",
            "c": false
          }
        ]
      },
      {
        "id": "iq4",
        "text": "Chess is often used to measure which skill?",
        "options": [
          {
            "t": "Strength",
            "c": false
          },
          {
            "t": "Strategic thinking",
            "c": true
          },
          {
            "t": "Speed",
            "c": false
          },
          {
            "t": "Memory only",
            "c": false
          }
        ]
      },
      {
        "id": "iq5",
        "text": "Who is known for developing the light bulb?",
        "options": [
          {
            "t": "Thomas Edison",
            "c": true
          },
          {
            "t": "Alexander Bell",
            "c": false
          },
          {
            "t": "Benjamin Franklin",
            "c": false
          },
          {
            "t": "James Watt",
            "c": false
          }
        ]
      },
      {
        "id": "iq6",
        "text": "What does 'logic' primarily deal with?",
        "options": [
          {
            "t": "Emotions",
            "c": false
          },
          {
            "t": "Reasoning and argument structure",
            "c": true
          },
          {
            "t": "Random guessing",
            "c": false
          },
          {
            "t": "Physical strength",
            "c": false
          }
        ]
      },
      {
        "id": "iq7",
        "text": "Which skill helps most when solving a riddle?",
        "options": [
          {
            "t": "Pattern recognition",
            "c": true
          },
          {
            "t": "Luck",
            "c": false
          },
          {
            "t": "Speed reading only",
            "c": false
          },
          {
            "t": "Guessing randomly",
            "c": false
          }
        ]
      },
      {
        "id": "iq8",
        "text": "What is a synonym for 'intelligent'?",
        "options": [
          {
            "t": "Sluggish",
            "c": false
          },
          {
            "t": "Sharp-minded",
            "c": true
          },
          {
            "t": "Careless",
            "c": false
          },
          {
            "t": "Forgetful",
            "c": false
          }
        ]
      },
      {
        "id": "iq9",
        "text": "Who is credited with formulating the laws of motion?",
        "options": [
          {
            "t": "Isaac Newton",
            "c": true
          },
          {
            "t": "Charles Darwin",
            "c": false
          },
          {
            "t": "Marie Curie",
            "c": false
          },
          {
            "t": "Louis Pasteur",
            "c": false
          }
        ]
      },
      {
        "id": "iq10",
        "text": "A person good at solving abstract problems is often called...",
        "options": [
          {
            "t": "Analytical",
            "c": true
          },
          {
            "t": "Impulsive",
            "c": false
          },
          {
            "t": "Careless",
            "c": false
          },
          {
            "t": "Distracted",
            "c": false
          }
        ]
      },
      {
        "id": "iq11",
        "text": "What does 'IQ' measure in a general sense?",
        "options": [
          {
            "t": "Cognitive/reasoning ability",
            "c": true
          },
          {
            "t": "Physical strength",
            "c": false
          },
          {
            "t": "Emotional state",
            "c": false
          },
          {
            "t": "Wealth",
            "c": false
          }
        ]
      },
      {
        "id": "iq12",
        "text": "Which of these best describes 'lateral thinking'?",
        "options": [
          {
            "t": "Solving problems through indirect/creative approaches",
            "c": true
          },
          {
            "t": "Memorizing facts",
            "c": false
          },
          {
            "t": "Following strict rules only",
            "c": false
          },
          {
            "t": "Guessing randomly",
            "c": false
          }
        ]
      },
      {
        "id": "iq13",
        "text": "What is the term for reasoning from general principles to a specific conclusion?",
        "options": [
          {
            "t": "Deductive reasoning",
            "c": true
          },
          {
            "t": "Inductive reasoning",
            "c": false
          },
          {
            "t": "Guessing",
            "c": false
          },
          {
            "t": "Emotional reasoning",
            "c": false
          }
        ]
      },
      {
        "id": "iq14",
        "text": "A sequence that reads the same forwards and backwards is called a?",
        "options": [
          {
            "t": "Palindrome",
            "c": true
          },
          {
            "t": "Anagram",
            "c": false
          },
          {
            "t": "Acronym",
            "c": false
          },
          {
            "t": "Synonym",
            "c": false
          }
        ]
      },
      {
        "id": "iq15",
        "text": "Which skill helps most when solving a Sudoku puzzle?",
        "options": [
          {
            "t": "Logical deduction",
            "c": true
          },
          {
            "t": "Physical speed",
            "c": false
          },
          {
            "t": "Memorization of stories",
            "c": false
          },
          {
            "t": "Luck",
            "c": false
          }
        ]
      },
      {
        "id": "iq16",
        "text": "What term describes learning from specific examples to form a general rule?",
        "options": [
          {
            "t": "Inductive reasoning",
            "c": true
          },
          {
            "t": "Deductive reasoning",
            "c": false
          },
          {
            "t": "Circular reasoning",
            "c": false
          },
          {
            "t": "False reasoning",
            "c": false
          }
        ]
      },
      {
        "id": "iq17",
        "text": "Which of these is an example of a logical fallacy?",
        "options": [
          {
            "t": "Attacking the person instead of the argument",
            "c": true
          },
          {
            "t": "Citing solid evidence",
            "c": false
          },
          {
            "t": "Using a valid syllogism",
            "c": false
          },
          {
            "t": "Peer review",
            "c": false
          }
        ]
      },
      {
        "id": "iq18",
        "text": "What is the term for a word that sounds the same as another but has a different meaning?",
        "options": [
          {
            "t": "Homophone",
            "c": true
          },
          {
            "t": "Synonym",
            "c": false
          },
          {
            "t": "Antonym",
            "c": false
          },
          {
            "t": "Palindrome",
            "c": false
          }
        ]
      },
      {
        "id": "iq19",
        "text": "Which famous test is commonly used to estimate a person's intelligence quotient?",
        "options": [
          {
            "t": "The Stanford-Binet or WAIS test",
            "c": true
          },
          {
            "t": "The bar exam",
            "c": false
          },
          {
            "t": "A blood test",
            "c": false
          },
          {
            "t": "A vision test",
            "c": false
          }
        ]
      },
      {
        "id": "iq20",
        "text": "What cognitive skill helps you remember a phone number briefly before dialing it?",
        "options": [
          {
            "t": "Short-term/working memory",
            "c": true
          },
          {
            "t": "Long-term memory only",
            "c": false
          },
          {
            "t": "Muscle memory",
            "c": false
          },
          {
            "t": "Emotional memory",
            "c": false
          }
        ]
      },
      {
        "id": "iq21",
        "text": "Which of these best demonstrates abstract thinking?",
        "options": [
          {
            "t": "Understanding metaphors and symbols",
            "c": true
          },
          {
            "t": "Only following literal instructions",
            "c": false
          },
          {
            "t": "Repeating memorized facts",
            "c": false
          },
          {
            "t": "Copying others exactly",
            "c": false
          }
        ]
      },
      {
        "id": "iq22",
        "text": "What is the term for a puzzle that requires filling a grid so every row, column, and box contains 1-9 once?",
        "options": [
          {
            "t": "Sudoku",
            "c": true
          },
          {
            "t": "Crossword",
            "c": false
          },
          {
            "t": "Chess problem",
            "c": false
          },
          {
            "t": "Anagram",
            "c": false
          }
        ]
      },
      {
        "id": "iq23",
        "text": "Which of these is a classic sign of strong problem-solving skills?",
        "options": [
          {
            "t": "Breaking a big problem into smaller parts",
            "c": true
          },
          {
            "t": "Avoiding all challenges",
            "c": false
          },
          {
            "t": "Ignoring evidence",
            "c": false
          },
          {
            "t": "Acting purely on impulse",
            "c": false
          }
        ]
      },
      {
        "id": "iq24",
        "text": "What do we call the ability to understand and manage one's own emotions and others'?",
        "options": [
          {
            "t": "Emotional intelligence",
            "c": true
          },
          {
            "t": "Logical intelligence only",
            "c": false
          },
          {
            "t": "Physical intelligence",
            "c": false
          },
          {
            "t": "Verbal intelligence only",
            "c": false
          }
        ]
      },
      {
        "id": "iq25",
        "text": "Which strategy is most effective for solving a maze puzzle?",
        "options": [
          {
            "t": "Systematically tracing paths and eliminating dead ends",
            "c": true
          },
          {
            "t": "Guessing randomly every time",
            "c": false
          },
          {
            "t": "Ignoring walls",
            "c": false
          },
          {
            "t": "Closing your eyes",
            "c": false
          }
        ]
      },
      {
        "id": "iq26",
        "text": "What term describes a statement that is true by definition, like 'all bachelors are unmarried'?",
        "options": [
          {
            "t": "A tautology/analytic truth",
            "c": true
          },
          {
            "t": "A paradox",
            "c": false
          },
          {
            "t": "A contradiction",
            "c": false
          },
          {
            "t": "A hypothesis",
            "c": false
          }
        ]
      },
      {
        "id": "iq27",
        "text": "Which of these numbers does not belong: 2, 3, 5, 7, 9?",
        "options": [
          {
            "t": "9 (not prime)",
            "c": true
          },
          {
            "t": "2",
            "c": false
          },
          {
            "t": "3",
            "c": false
          },
          {
            "t": "7",
            "c": false
          }
        ]
      },
      {
        "id": "iq28",
        "text": "What is the term for solving problems by trial and error methodically?",
        "options": [
          {
            "t": "Heuristic approach",
            "c": true
          },
          {
            "t": "Blind guessing",
            "c": false
          },
          {
            "t": "Memorization",
            "c": false
          },
          {
            "t": "Avoidance",
            "c": false
          }
        ]
      },
      {
        "id": "iq29",
        "text": "Which skill is most tested by a pattern-completion question (like image sequences)?",
        "options": [
          {
            "t": "Visual-spatial reasoning",
            "c": true
          },
          {
            "t": "Verbal fluency only",
            "c": false
          },
          {
            "t": "Physical coordination",
            "c": false
          },
          {
            "t": "Long-term memory only",
            "c": false
          }
        ]
      },
      {
        "id": "iq30",
        "text": "What is it called when someone jumps to a conclusion without enough evidence?",
        "options": [
          {
            "t": "A hasty generalization",
            "c": true
          },
          {
            "t": "A valid deduction",
            "c": false
          },
          {
            "t": "An axiom",
            "c": false
          },
          {
            "t": "A theorem",
            "c": false
          }
        ]
      }
    ]
  },
  {
    "slug": "history-quiz",
    "tag": "History",
    "title": "History Quiz",
    "description": "Key moments and figures that shaped the world.",
    "minutes": 3,
    "round_size": 5,
    "questions": [
      {
        "id": "hq1",
        "text": "Which ancient civilization built the pyramids of Giza?",
        "options": [
          {
            "t": "Romans",
            "c": false
          },
          {
            "t": "Egyptians",
            "c": true
          },
          {
            "t": "Greeks",
            "c": false
          },
          {
            "t": "Persians",
            "c": false
          }
        ]
      },
      {
        "id": "hq2",
        "text": "In what century did World War II take place?",
        "options": [
          {
            "t": "19th century",
            "c": false
          },
          {
            "t": "20th century",
            "c": true
          },
          {
            "t": "21st century",
            "c": false
          },
          {
            "t": "18th century",
            "c": false
          }
        ]
      },
      {
        "id": "hq3",
        "text": "Who was the first President of the United States?",
        "options": [
          {
            "t": "Thomas Jefferson",
            "c": false
          },
          {
            "t": "George Washington",
            "c": true
          },
          {
            "t": "Abraham Lincoln",
            "c": false
          },
          {
            "t": "John Adams",
            "c": false
          }
        ]
      },
      {
        "id": "hq4",
        "text": "The Great Wall was built primarily in which country?",
        "options": [
          {
            "t": "India",
            "c": false
          },
          {
            "t": "China",
            "c": true
          },
          {
            "t": "Japan",
            "c": false
          },
          {
            "t": "Mongolia",
            "c": false
          }
        ]
      },
      {
        "id": "hq5",
        "text": "Which empire was ruled by Julius Caesar?",
        "options": [
          {
            "t": "Roman Empire",
            "c": true
          },
          {
            "t": "Ottoman Empire",
            "c": false
          },
          {
            "t": "British Empire",
            "c": false
          },
          {
            "t": "Persian Empire",
            "c": false
          }
        ]
      },
      {
        "id": "hq6",
        "text": "What year did Ghana gain independence?",
        "options": [
          {
            "t": "1957",
            "c": true
          },
          {
            "t": "1963",
            "c": false
          },
          {
            "t": "1945",
            "c": false
          },
          {
            "t": "1970",
            "c": false
          }
        ]
      },
      {
        "id": "hq7",
        "text": "The Renaissance period is most associated with which continent?",
        "options": [
          {
            "t": "Africa",
            "c": false
          },
          {
            "t": "Europe",
            "c": true
          },
          {
            "t": "Asia",
            "c": false
          },
          {
            "t": "South America",
            "c": false
          }
        ]
      },
      {
        "id": "hq8",
        "text": "Who is known for leading the Indian independence movement through non-violence?",
        "options": [
          {
            "t": "Mahatma Gandhi",
            "c": true
          },
          {
            "t": "Nelson Mandela",
            "c": false
          },
          {
            "t": "Winston Churchill",
            "c": false
          },
          {
            "t": "Kwame Nkrumah",
            "c": false
          }
        ]
      },
      {
        "id": "hq9",
        "text": "The Cold War was primarily a standoff between which two powers?",
        "options": [
          {
            "t": "USA and USSR",
            "c": true
          },
          {
            "t": "UK and France",
            "c": false
          },
          {
            "t": "China and Japan",
            "c": false
          },
          {
            "t": "Germany and Italy",
            "c": false
          }
        ]
      },
      {
        "id": "hq10",
        "text": "Who was Ghana's first President?",
        "options": [
          {
            "t": "Kwame Nkrumah",
            "c": true
          },
          {
            "t": "Jerry Rawlings",
            "c": false
          },
          {
            "t": "Kofi Annan",
            "c": false
          },
          {
            "t": "John Kufuor",
            "c": false
          }
        ]
      },
      {
        "id": "hq11",
        "text": "Which war was fought between the North and South United States (1861-1865)?",
        "options": [
          {
            "t": "The American Civil War",
            "c": true
          },
          {
            "t": "World War I",
            "c": false
          },
          {
            "t": "The Revolutionary War",
            "c": false
          },
          {
            "t": "The War of 1812",
            "c": false
          }
        ]
      },
      {
        "id": "hq12",
        "text": "Which empire was ruled by Genghis Khan?",
        "options": [
          {
            "t": "The Mongol Empire",
            "c": true
          },
          {
            "t": "The Roman Empire",
            "c": false
          },
          {
            "t": "The Ottoman Empire",
            "c": false
          },
          {
            "t": "The British Empire",
            "c": false
          }
        ]
      },
      {
        "id": "hq13",
        "text": "In what year did World War II end?",
        "options": [
          {
            "t": "1945",
            "c": true
          },
          {
            "t": "1939",
            "c": false
          },
          {
            "t": "1918",
            "c": false
          },
          {
            "t": "1950",
            "c": false
          }
        ]
      },
      {
        "id": "hq14",
        "text": "Who was the ancient Egyptian queen known for her alliance with Julius Caesar and Mark Antony?",
        "options": [
          {
            "t": "Cleopatra",
            "c": true
          },
          {
            "t": "Nefertiti",
            "c": false
          },
          {
            "t": "Hatshepsut",
            "c": false
          },
          {
            "t": "Isis",
            "c": false
          }
        ]
      },
      {
        "id": "hq15",
        "text": "What ancient wonder was located in the city of Giza?",
        "options": [
          {
            "t": "The Great Pyramid",
            "c": true
          },
          {
            "t": "The Colossus of Rhodes",
            "c": false
          },
          {
            "t": "The Hanging Gardens",
            "c": false
          },
          {
            "t": "The Lighthouse of Alexandria",
            "c": false
          }
        ]
      },
      {
        "id": "hq16",
        "text": "Which country was the first to industrialize during the Industrial Revolution?",
        "options": [
          {
            "t": "Great Britain",
            "c": true
          },
          {
            "t": "United States",
            "c": false
          },
          {
            "t": "France",
            "c": false
          },
          {
            "t": "Germany",
            "c": false
          }
        ]
      },
      {
        "id": "hq17",
        "text": "What was the name of the ship that carried the Pilgrims to America in 1620?",
        "options": [
          {
            "t": "The Mayflower",
            "c": true
          },
          {
            "t": "The Santa Maria",
            "c": false
          },
          {
            "t": "The Titanic",
            "c": false
          },
          {
            "t": "The Nina",
            "c": false
          }
        ]
      },
      {
        "id": "hq18",
        "text": "Which African kingdom was famous for its wealth under ruler Mansa Musa?",
        "options": [
          {
            "t": "The Mali Empire",
            "c": true
          },
          {
            "t": "The Zulu Kingdom",
            "c": false
          },
          {
            "t": "The Kingdom of Kush",
            "c": false
          },
          {
            "t": "The Kingdom of Aksum",
            "c": false
          }
        ]
      },
      {
        "id": "hq19",
        "text": "What event in 1789 marked the start of major political upheaval in France?",
        "options": [
          {
            "t": "The French Revolution",
            "c": true
          },
          {
            "t": "The Napoleonic Wars",
            "c": false
          },
          {
            "t": "The Hundred Years' War",
            "c": false
          },
          {
            "t": "The Reign of Terror alone",
            "c": false
          }
        ]
      },
      {
        "id": "hq20",
        "text": "Who was the British prime minister during most of World War II?",
        "options": [
          {
            "t": "Winston Churchill",
            "c": true
          },
          {
            "t": "Neville Chamberlain",
            "c": false
          },
          {
            "t": "Margaret Thatcher",
            "c": false
          },
          {
            "t": "Tony Blair",
            "c": false
          }
        ]
      },
      {
        "id": "hq21",
        "text": "Which ancient civilization developed the earliest known writing system, cuneiform?",
        "options": [
          {
            "t": "The Sumerians",
            "c": true
          },
          {
            "t": "The Egyptians",
            "c": false
          },
          {
            "t": "The Greeks",
            "c": false
          },
          {
            "t": "The Romans",
            "c": false
          }
        ]
      },
      {
        "id": "hq22",
        "text": "What wall divided a European city from 1961 to 1989?",
        "options": [
          {
            "t": "The Berlin Wall",
            "c": true
          },
          {
            "t": "The Great Wall",
            "c": false
          },
          {
            "t": "Hadrian's Wall",
            "c": false
          },
          {
            "t": "The Atlantic Wall",
            "c": false
          }
        ]
      },
      {
        "id": "hq23",
        "text": "Which explorer is credited with reaching the Americas in 1492?",
        "options": [
          {
            "t": "Christopher Columbus",
            "c": true
          },
          {
            "t": "Vasco da Gama",
            "c": false
          },
          {
            "t": "Ferdinand Magellan",
            "c": false
          },
          {
            "t": "Marco Polo",
            "c": false
          }
        ]
      },
      {
        "id": "hq24",
        "text": "What was the name of the global conflict that took place from 1914 to 1918?",
        "options": [
          {
            "t": "World War I",
            "c": true
          },
          {
            "t": "World War II",
            "c": false
          },
          {
            "t": "The Cold War",
            "c": false
          },
          {
            "t": "The Korean War",
            "c": false
          }
        ]
      },
      {
        "id": "hq25",
        "text": "Which South African leader spent 27 years in prison before becoming president?",
        "options": [
          {
            "t": "Nelson Mandela",
            "c": true
          },
          {
            "t": "Desmond Tutu",
            "c": false
          },
          {
            "t": "Kwame Nkrumah",
            "c": false
          },
          {
            "t": "Jomo Kenyatta",
            "c": false
          }
        ]
      },
      {
        "id": "hq26",
        "text": "What ancient Greek city-state is credited with creating democracy?",
        "options": [
          {
            "t": "Athens",
            "c": true
          },
          {
            "t": "Sparta",
            "c": false
          },
          {
            "t": "Corinth",
            "c": false
          },
          {
            "t": "Thebes",
            "c": false
          }
        ]
      },
      {
        "id": "hq27",
        "text": "Which dynasty built the Terracotta Army in China?",
        "options": [
          {
            "t": "The Qin Dynasty",
            "c": true
          },
          {
            "t": "The Ming Dynasty",
            "c": false
          },
          {
            "t": "The Han Dynasty",
            "c": false
          },
          {
            "t": "The Tang Dynasty",
            "c": false
          }
        ]
      },
      {
        "id": "hq28",
        "text": "What treaty formally ended World War I in 1919?",
        "options": [
          {
            "t": "The Treaty of Versailles",
            "c": true
          },
          {
            "t": "The Treaty of Paris",
            "c": false
          },
          {
            "t": "The Treaty of Rome",
            "c": false
          },
          {
            "t": "The Treaty of Ghent",
            "c": false
          }
        ]
      },
      {
        "id": "hq29",
        "text": "Who was the first person to walk on the moon in 1969?",
        "options": [
          {
            "t": "Neil Armstrong",
            "c": true
          },
          {
            "t": "Buzz Aldrin",
            "c": false
          },
          {
            "t": "Yuri Gagarin",
            "c": false
          },
          {
            "t": "John Glenn",
            "c": false
          }
        ]
      },
      {
        "id": "hq30",
        "text": "Which African leader led Ghana to become the first sub-Saharan African country to gain independence from colonial rule?",
        "options": [
          {
            "t": "Kwame Nkrumah",
            "c": true
          },
          {
            "t": "Nelson Mandela",
            "c": false
          },
          {
            "t": "Julius Nyerere",
            "c": false
          },
          {
            "t": "Haile Selassie",
            "c": false
          }
        ]
      }
    ]
  },
  {
    "slug": "geography-quiz",
    "tag": "Geography",
    "title": "Geography Quiz",
    "description": "Continents, capitals, and everything in between.",
    "minutes": 3,
    "round_size": 5,
    "questions": [
      {
        "id": "gq1",
        "text": "What is the capital of Ghana?",
        "options": [
          {
            "t": "Kumasi",
            "c": false
          },
          {
            "t": "Accra",
            "c": true
          },
          {
            "t": "Takoradi",
            "c": false
          },
          {
            "t": "Tamale",
            "c": false
          }
        ]
      },
      {
        "id": "gq2",
        "text": "Which is the largest continent by area?",
        "options": [
          {
            "t": "Africa",
            "c": false
          },
          {
            "t": "Asia",
            "c": true
          },
          {
            "t": "Europe",
            "c": false
          },
          {
            "t": "Australia",
            "c": false
          }
        ]
      },
      {
        "id": "gq3",
        "text": "Which river is the longest in the world?",
        "options": [
          {
            "t": "Amazon",
            "c": false
          },
          {
            "t": "Nile",
            "c": true
          },
          {
            "t": "Congo",
            "c": false
          },
          {
            "t": "Volta",
            "c": false
          }
        ]
      },
      {
        "id": "gq4",
        "text": "Which desert is the largest hot desert on Earth?",
        "options": [
          {
            "t": "Sahara",
            "c": true
          },
          {
            "t": "Gobi",
            "c": false
          },
          {
            "t": "Kalahari",
            "c": false
          },
          {
            "t": "Atacama",
            "c": false
          }
        ]
      },
      {
        "id": "gq5",
        "text": "Mount Everest is located in which mountain range?",
        "options": [
          {
            "t": "Andes",
            "c": false
          },
          {
            "t": "Himalayas",
            "c": true
          },
          {
            "t": "Alps",
            "c": false
          },
          {
            "t": "Rockies",
            "c": false
          }
        ]
      },
      {
        "id": "gq6",
        "text": "Which country is known as the Land of the Rising Sun?",
        "options": [
          {
            "t": "China",
            "c": false
          },
          {
            "t": "Japan",
            "c": true
          },
          {
            "t": "South Korea",
            "c": false
          },
          {
            "t": "Thailand",
            "c": false
          }
        ]
      },
      {
        "id": "gq7",
        "text": "Which ocean is the largest?",
        "options": [
          {
            "t": "Atlantic",
            "c": false
          },
          {
            "t": "Indian",
            "c": false
          },
          {
            "t": "Pacific",
            "c": true
          },
          {
            "t": "Arctic",
            "c": false
          }
        ]
      },
      {
        "id": "gq8",
        "text": "Which African country is entirely surrounded by South Africa?",
        "options": [
          {
            "t": "Lesotho",
            "c": true
          },
          {
            "t": "Eswatini",
            "c": false
          },
          {
            "t": "Botswana",
            "c": false
          },
          {
            "t": "Zimbabwe",
            "c": false
          }
        ]
      },
      {
        "id": "gq9",
        "text": "Which country has the most population in the world?",
        "options": [
          {
            "t": "USA",
            "c": false
          },
          {
            "t": "India",
            "c": true
          },
          {
            "t": "China",
            "c": false
          },
          {
            "t": "Indonesia",
            "c": false
          }
        ]
      },
      {
        "id": "gq10",
        "text": "Which line divides the Earth into Northern and Southern Hemispheres?",
        "options": [
          {
            "t": "Prime Meridian",
            "c": false
          },
          {
            "t": "Equator",
            "c": true
          },
          {
            "t": "Tropic of Cancer",
            "c": false
          },
          {
            "t": "International Date Line",
            "c": false
          }
        ]
      },
      {
        "id": "gq11",
        "text": "What is the smallest country in the world by area?",
        "options": [
          {
            "t": "Vatican City",
            "c": true
          },
          {
            "t": "Monaco",
            "c": false
          },
          {
            "t": "San Marino",
            "c": false
          },
          {
            "t": "Liechtenstein",
            "c": false
          }
        ]
      },
      {
        "id": "gq12",
        "text": "Which country has the most natural lakes in the world?",
        "options": [
          {
            "t": "Canada",
            "c": true
          },
          {
            "t": "Russia",
            "c": false
          },
          {
            "t": "United States",
            "c": false
          },
          {
            "t": "Finland",
            "c": false
          }
        ]
      },
      {
        "id": "gq13",
        "text": "What is the longest mountain range in the world?",
        "options": [
          {
            "t": "The Andes",
            "c": true
          },
          {
            "t": "The Rockies",
            "c": false
          },
          {
            "t": "The Himalayas",
            "c": false
          },
          {
            "t": "The Alps",
            "c": false
          }
        ]
      },
      {
        "id": "gq14",
        "text": "Which African country was formerly known as Abyssinia?",
        "options": [
          {
            "t": "Ethiopia",
            "c": true
          },
          {
            "t": "Eritrea",
            "c": false
          },
          {
            "t": "Sudan",
            "c": false
          },
          {
            "t": "Somalia",
            "c": false
          }
        ]
      },
      {
        "id": "gq15",
        "text": "What is the capital city of Japan?",
        "options": [
          {
            "t": "Tokyo",
            "c": true
          },
          {
            "t": "Kyoto",
            "c": false
          },
          {
            "t": "Osaka",
            "c": false
          },
          {
            "t": "Yokohama",
            "c": false
          }
        ]
      },
      {
        "id": "gq16",
        "text": "Which continent is the driest inhabited continent on Earth?",
        "options": [
          {
            "t": "Australia",
            "c": true
          },
          {
            "t": "Africa",
            "c": false
          },
          {
            "t": "Asia",
            "c": false
          },
          {
            "t": "South America",
            "c": false
          }
        ]
      },
      {
        "id": "gq17",
        "text": "What is the capital of Nigeria?",
        "options": [
          {
            "t": "Abuja",
            "c": true
          },
          {
            "t": "Lagos",
            "c": false
          },
          {
            "t": "Kano",
            "c": false
          },
          {
            "t": "Ibadan",
            "c": false
          }
        ]
      },
      {
        "id": "gq18",
        "text": "Which sea is the saltiest large body of water in the world?",
        "options": [
          {
            "t": "The Dead Sea",
            "c": true
          },
          {
            "t": "The Red Sea",
            "c": false
          },
          {
            "t": "The Black Sea",
            "c": false
          },
          {
            "t": "The Caspian Sea",
            "c": false
          }
        ]
      },
      {
        "id": "gq19",
        "text": "What is the largest island in the world?",
        "options": [
          {
            "t": "Greenland",
            "c": true
          },
          {
            "t": "Madagascar",
            "c": false
          },
          {
            "t": "Borneo",
            "c": false
          },
          {
            "t": "New Guinea",
            "c": false
          }
        ]
      },
      {
        "id": "gq20",
        "text": "Which strait separates Europe and Africa at their closest point?",
        "options": [
          {
            "t": "The Strait of Gibraltar",
            "c": true
          },
          {
            "t": "The Bosphorus",
            "c": false
          },
          {
            "t": "The Strait of Hormuz",
            "c": false
          },
          {
            "t": "The Bering Strait",
            "c": false
          }
        ]
      },
      {
        "id": "gq21",
        "text": "What is the capital of Kenya?",
        "options": [
          {
            "t": "Nairobi",
            "c": true
          },
          {
            "t": "Mombasa",
            "c": false
          },
          {
            "t": "Kisumu",
            "c": false
          },
          {
            "t": "Nakuru",
            "c": false
          }
        ]
      },
      {
        "id": "gq22",
        "text": "Which country is both in Europe and Asia?",
        "options": [
          {
            "t": "Turkey",
            "c": true
          },
          {
            "t": "Egypt only",
            "c": false
          },
          {
            "t": "Greece",
            "c": false
          },
          {
            "t": "Morocco",
            "c": false
          }
        ]
      },
      {
        "id": "gq23",
        "text": "What is the term for a large area of flat grassland, especially in Africa?",
        "options": [
          {
            "t": "Savanna",
            "c": true
          },
          {
            "t": "Tundra",
            "c": false
          },
          {
            "t": "Rainforest",
            "c": false
          },
          {
            "t": "Steppe only",
            "c": false
          }
        ]
      },
      {
        "id": "gq24",
        "text": "Which country has the largest population in Africa?",
        "options": [
          {
            "t": "Nigeria",
            "c": true
          },
          {
            "t": "Egypt",
            "c": false
          },
          {
            "t": "Ethiopia",
            "c": false
          },
          {
            "t": "South Africa",
            "c": false
          }
        ]
      },
      {
        "id": "gq25",
        "text": "What is the world's longest river by most measurements?",
        "options": [
          {
            "t": "The Nile",
            "c": true
          },
          {
            "t": "The Amazon",
            "c": false
          },
          {
            "t": "The Yangtze",
            "c": false
          },
          {
            "t": "The Mississippi",
            "c": false
          }
        ]
      },
      {
        "id": "gq26",
        "text": "Which US state is both the largest by area and includes Mount Denali?",
        "options": [
          {
            "t": "Alaska",
            "c": true
          },
          {
            "t": "Texas",
            "c": false
          },
          {
            "t": "California",
            "c": false
          },
          {
            "t": "Montana",
            "c": false
          }
        ]
      },
      {
        "id": "gq27",
        "text": "What is the name of the imaginary line at 0 degrees longitude?",
        "options": [
          {
            "t": "The Prime Meridian",
            "c": true
          },
          {
            "t": "The Equator",
            "c": false
          },
          {
            "t": "The Tropic of Cancer",
            "c": false
          },
          {
            "t": "The International Date Line",
            "c": false
          }
        ]
      },
      {
        "id": "gq28",
        "text": "Which country is known as the 'Land Down Under'?",
        "options": [
          {
            "t": "Australia",
            "c": true
          },
          {
            "t": "New Zealand",
            "c": false
          },
          {
            "t": "South Africa",
            "c": false
          },
          {
            "t": "Argentina",
            "c": false
          }
        ]
      },
      {
        "id": "gq29",
        "text": "What is the capital city of Ghana's neighboring country, Ivory Coast (C\u00f4te d'Ivoire)?",
        "options": [
          {
            "t": "Yamoussoukro",
            "c": true
          },
          {
            "t": "Abidjan only",
            "c": false
          },
          {
            "t": "Accra",
            "c": false
          },
          {
            "t": "Lom\u00e9",
            "c": false
          }
        ]
      },
      {
        "id": "gq30",
        "text": "Which mountain is the tallest in Africa?",
        "options": [
          {
            "t": "Mount Kilimanjaro",
            "c": true
          },
          {
            "t": "Mount Kenya",
            "c": false
          },
          {
            "t": "Mount Meru",
            "c": false
          },
          {
            "t": "Table Mountain",
            "c": false
          }
        ]
      }
    ]
  },
  {
    "slug": "pop-culture-quiz",
    "tag": "Entertainment",
    "title": "Pop Culture & Movies",
    "description": "Music, movies, and moments everyone's talking about.",
    "minutes": 2,
    "round_size": 5,
    "questions": [
      {
        "id": "pc1",
        "text": "What do you call a movie that continues a story from an earlier film?",
        "options": [
          {
            "t": "Prequel",
            "c": false
          },
          {
            "t": "Sequel",
            "c": true
          },
          {
            "t": "Remake",
            "c": false
          },
          {
            "t": "Spin-off",
            "c": false
          }
        ]
      },
      {
        "id": "pc2",
        "text": "Which award is considered the top honor in the film industry?",
        "options": [
          {
            "t": "Grammy",
            "c": false
          },
          {
            "t": "Oscar",
            "c": true
          },
          {
            "t": "Emmy",
            "c": false
          },
          {
            "t": "Tony",
            "c": false
          }
        ]
      },
      {
        "id": "pc3",
        "text": "What is the term for a song that reaches number one on the charts?",
        "options": [
          {
            "t": "Chart-topper",
            "c": true
          },
          {
            "t": "B-side",
            "c": false
          },
          {
            "t": "Remix",
            "c": false
          },
          {
            "t": "Cover",
            "c": false
          }
        ]
      },
      {
        "id": "pc4",
        "text": "Which of these describes a 'plot twist'?",
        "options": [
          {
            "t": "A predictable ending",
            "c": false
          },
          {
            "t": "An unexpected turn in the story",
            "c": true
          },
          {
            "t": "The opening scene",
            "c": false
          },
          {
            "t": "A movie's soundtrack",
            "c": false
          }
        ]
      },
      {
        "id": "pc5",
        "text": "What do we call an actor who plays the main character?",
        "options": [
          {
            "t": "Extra",
            "c": false
          },
          {
            "t": "Protagonist",
            "c": true
          },
          {
            "t": "Understudy",
            "c": false
          },
          {
            "t": "Director",
            "c": false
          }
        ]
      },
      {
        "id": "pc6",
        "text": "Animated films are primarily created using...",
        "options": [
          {
            "t": "Live actors only",
            "c": false
          },
          {
            "t": "Drawings or computer animation",
            "c": true
          },
          {
            "t": "Radio scripts",
            "c": false
          },
          {
            "t": "Stage plays",
            "c": false
          }
        ]
      },
      {
        "id": "pc7",
        "text": "What is a 'blockbuster'?",
        "options": [
          {
            "t": "A low-budget indie film",
            "c": false
          },
          {
            "t": "A hugely popular, high-earning film",
            "c": true
          },
          {
            "t": "A short film",
            "c": false
          },
          {
            "t": "A documentary",
            "c": false
          }
        ]
      },
      {
        "id": "pc8",
        "text": "Which term describes music played live without recording?",
        "options": [
          {
            "t": "Live performance",
            "c": true
          },
          {
            "t": "Studio session",
            "c": false
          },
          {
            "t": "Remastered track",
            "c": false
          },
          {
            "t": "Instrumental",
            "c": false
          }
        ]
      },
      {
        "id": "pc9",
        "text": "What do fans call the community around a show or artist?",
        "options": [
          {
            "t": "Fandom",
            "c": true
          },
          {
            "t": "Cast",
            "c": false
          },
          {
            "t": "Crew",
            "c": false
          },
          {
            "t": "Studio",
            "c": false
          }
        ]
      },
      {
        "id": "pc10",
        "text": "A movie critic's review typically focuses on...",
        "options": [
          {
            "t": "Ticket prices",
            "c": false
          },
          {
            "t": "The quality of the film",
            "c": true
          },
          {
            "t": "Cinema snacks",
            "c": false
          },
          {
            "t": "Parking availability",
            "c": false
          }
        ]
      },
      {
        "id": "pc11",
        "text": "What do we call a movie made specifically to scare its audience?",
        "options": [
          {
            "t": "A horror film",
            "c": true
          },
          {
            "t": "A drama",
            "c": false
          },
          {
            "t": "A documentary",
            "c": false
          },
          {
            "t": "A romance",
            "c": false
          }
        ]
      },
      {
        "id": "pc12",
        "text": "What term describes an actor's very first film role?",
        "options": [
          {
            "t": "Film debut",
            "c": true
          },
          {
            "t": "Encore",
            "c": false
          },
          {
            "t": "Cameo only",
            "c": false
          },
          {
            "t": "Understudy role",
            "c": false
          }
        ]
      },
      {
        "id": "pc13",
        "text": "What is a 'soundtrack'?",
        "options": [
          {
            "t": "The music featured in a film or show",
            "c": true
          },
          {
            "t": "The script of a movie",
            "c": false
          },
          {
            "t": "The film's box office earnings",
            "c": false
          },
          {
            "t": "The director's notes",
            "c": false
          }
        ]
      },
      {
        "id": "pc14",
        "text": "What do we call a short, uncredited appearance by a celebrity in a film?",
        "options": [
          {
            "t": "A cameo",
            "c": true
          },
          {
            "t": "A lead role",
            "c": false
          },
          {
            "t": "An extra role only",
            "c": false
          },
          {
            "t": "A voiceover always",
            "c": false
          }
        ]
      },
      {
        "id": "pc15",
        "text": "What is the term for adapting a book into a movie?",
        "options": [
          {
            "t": "A film adaptation",
            "c": true
          },
          {
            "t": "A remake only",
            "c": false
          },
          {
            "t": "A spin-off",
            "c": false
          },
          {
            "t": "A parody",
            "c": false
          }
        ]
      },
      {
        "id": "pc16",
        "text": "What do we call the person responsible for a film's overall creative vision?",
        "options": [
          {
            "t": "The director",
            "c": true
          },
          {
            "t": "The producer only",
            "c": false
          },
          {
            "t": "The editor",
            "c": false
          },
          {
            "t": "The screenwriter alone",
            "c": false
          }
        ]
      },
      {
        "id": "pc17",
        "text": "What is a 'franchise' in entertainment?",
        "options": [
          {
            "t": "A series of related films/shows sharing characters or a universe",
            "c": true
          },
          {
            "t": "A single stand-alone film",
            "c": false
          },
          {
            "t": "A film festival",
            "c": false
          },
          {
            "t": "A type of camera",
            "c": false
          }
        ]
      },
      {
        "id": "pc18",
        "text": "What term describes music performed without any instruments, voice only?",
        "options": [
          {
            "t": "A cappella",
            "c": true
          },
          {
            "t": "Instrumental",
            "c": false
          },
          {
            "t": "Remix",
            "c": false
          },
          {
            "t": "Orchestral",
            "c": false
          }
        ]
      },
      {
        "id": "pc19",
        "text": "What is a 'binge-watch'?",
        "options": [
          {
            "t": "Watching many episodes of a show in one sitting",
            "c": true
          },
          {
            "t": "Watching a movie in theaters",
            "c": false
          },
          {
            "t": "Reviewing a film critically",
            "c": false
          },
          {
            "t": "Watching with subtitles only",
            "c": false
          }
        ]
      },
      {
        "id": "pc20",
        "text": "What do we call an award given for outstanding achievement in television?",
        "options": [
          {
            "t": "An Emmy",
            "c": true
          },
          {
            "t": "An Oscar",
            "c": false
          },
          {
            "t": "A Grammy",
            "c": false
          },
          {
            "t": "A Tony",
            "c": false
          }
        ]
      },
      {
        "id": "pc21",
        "text": "What is a 'trailer' in the context of movies?",
        "options": [
          {
            "t": "A short preview advertising the film",
            "c": true
          },
          {
            "t": "The film's final scene",
            "c": false
          },
          {
            "t": "A behind-the-scenes documentary",
            "c": false
          },
          {
            "t": "The opening credits",
            "c": false
          }
        ]
      },
      {
        "id": "pc22",
        "text": "What term describes a song re-recorded in a different style?",
        "options": [
          {
            "t": "A remix or cover",
            "c": true
          },
          {
            "t": "A soundtrack",
            "c": false
          },
          {
            "t": "A demo",
            "c": false
          },
          {
            "t": "An encore",
            "c": false
          }
        ]
      },
      {
        "id": "pc23",
        "text": "What is the term for a story told entirely through pictures in sequence, like a comic?",
        "options": [
          {
            "t": "A graphic novel/comic",
            "c": true
          },
          {
            "t": "A screenplay",
            "c": false
          },
          {
            "t": "A novel",
            "c": false
          },
          {
            "t": "A biography",
            "c": false
          }
        ]
      },
      {
        "id": "pc24",
        "text": "What do we call a live event where fans meet celebrities and see panels, often for movies or games?",
        "options": [
          {
            "t": "A convention (con)",
            "c": true
          },
          {
            "t": "A premiere only",
            "c": false
          },
          {
            "t": "A press conference only",
            "c": false
          },
          {
            "t": "An audition",
            "c": false
          }
        ]
      },
      {
        "id": "pc25",
        "text": "What is the term for the main storyline running through a season of a TV show?",
        "options": [
          {
            "t": "A story arc",
            "c": true
          },
          {
            "t": "A subplot only",
            "c": false
          },
          {
            "t": "A cliffhanger only",
            "c": false
          },
          {
            "t": "A pilot",
            "c": false
          }
        ]
      },
      {
        "id": "pc26",
        "text": "What do we call music that is popular and widely played on the radio?",
        "options": [
          {
            "t": "Pop/mainstream music",
            "c": true
          },
          {
            "t": "Classical music only",
            "c": false
          },
          {
            "t": "Instrumental-only music",
            "c": false
          },
          {
            "t": "Folk music exclusively",
            "c": false
          }
        ]
      },
      {
        "id": "pc27",
        "text": "What is a 'spoiler'?",
        "options": [
          {
            "t": "Information that reveals plot details in advance",
            "c": true
          },
          {
            "t": "A film's soundtrack",
            "c": false
          },
          {
            "t": "A movie's title",
            "c": false
          },
          {
            "t": "A trailer",
            "c": false
          }
        ]
      },
      {
        "id": "pc28",
        "text": "What do we call the very first episode of a TV series, used to test audience interest?",
        "options": [
          {
            "t": "The pilot episode",
            "c": true
          },
          {
            "t": "The finale",
            "c": false
          },
          {
            "t": "A special episode",
            "c": false
          },
          {
            "t": "A recap episode",
            "c": false
          }
        ]
      },
      {
        "id": "pc29",
        "text": "What is the term for a film that continues the story but from before the original, chronologically?",
        "options": [
          {
            "t": "A prequel",
            "c": true
          },
          {
            "t": "A sequel",
            "c": false
          },
          {
            "t": "A reboot only",
            "c": false
          },
          {
            "t": "A remake",
            "c": false
          }
        ]
      },
      {
        "id": "pc30",
        "text": "What do we call a movie that retells an older film with a fresh cast and updated approach?",
        "options": [
          {
            "t": "A remake",
            "c": true
          },
          {
            "t": "A prequel only",
            "c": false
          },
          {
            "t": "A sequel",
            "c": false
          },
          {
            "t": "A spin-off only",
            "c": false
          }
        ]
      }
    ]
  }
]